flask_pydanql_api/__init__.py
flask_pydanql_api/routes.py
Flask_Pydanql_API-0.0.4a0.dist-info/METADATA
Flask_Pydanql_API-0.0.4a0.dist-info/WHEEL
Flask_Pydanql_API-0.0.4a0.dist-info/top_level.txt
Flask_Pydanql_API-0.0.4a0.dist-info/RECORD
