Metadata-Version: 2.1
Name: Flask-Pydanql-API
Version: 0.0.4a0
Home-page: https://blacktre.es
Author: Daniel Nümm
Author-email: oss@blacktre.es
Classifier: Programming Language :: Python :: 3
Classifier: License :: OSI Approved :: MIT License
Classifier: Operating System :: OS Independent
Requires-Dist: Flask
Requires-Dist: pydanql
